MANIFEST.in
README.rst
development.txt
requirements-server.txt
requirements.txt
setup.py
curdling/__init__.py
curdling/__main__.py
curdling/database.py
curdling/exceptions.py
curdling/freeze.py
curdling/index.py
curdling/install.py
curdling/mapping.py
curdling/signal.py
curdling/uninstall.py
curdling/util.py
curdling/version.py
curdling/wheel.py
curdling.egg-info/PKG-INFO
curdling.egg-info/SOURCES.txt
curdling.egg-info/dependency_links.txt
curdling.egg-info/entry_points.txt
curdling.egg-info/requires.txt
curdling.egg-info/top_level.txt
curdling/services/__init__.py
curdling/services/base.py
curdling/services/curdler.py
curdling/services/dependencer.py
curdling/services/downloader.py
curdling/services/installer.py
curdling/services/uploader.py
curdling/tool/__init__.py
curdling/web/__init__.py
curdling/web/__main__.py
curdling/web/templates/index.html