Metadata-Version: 1.1
Name: curdling
Version: 0.4.1
Summary: Concurrent package manager for Python
Home-page: https://github.com/clarete/curdling
Author: Lincoln Clarete
Author-email: lincoln@clarete.li
License: UNKNOWN
Platform: UNKNOWN
Classifier: Topic :: Software Development :: Build Tools
Classifier: Intended Audience :: Developers
Classifier: Intended Audience :: System Administrators
Classifier: Development Status :: 3 - Alpha
Classifier: Operating System :: OS Independent
Classifier: Programming Language :: Python
Classifier: Programming Language :: Python :: 2.6
Classifier: Programming Language :: Python :: 2.7
Classifier: Programming Language :: Python :: 3
Classifier: Programming Language :: Python :: 3.1
Classifier: Programming Language :: Python :: 3.2
Classifier: Programming Language :: Python :: 3.3
